{
  "updatedAt": "2026-07-24T10:07:45.569153+09:00",
  "domesticIndex": [
    {
      "itemCode": "KOSPI",
      "stockName": "코스피",
      "stockExchangeType": {
        "code": "KS",
        "zoneId": "Asia/Seoul",
        "nationType": "KOR",
        "delayTime": 0,
        "startTime": "0900",
        "endTime": "1530",
        "closePriceSendTime": "1630",
        "nameKor": "코스피",
        "nameEng": "KOSPI",
        "nationCode": "KOR",
        "nationName": "대한민국",
        "stockType": "domestic",
        "name": "KOSPI"
      },
      "closePrice": "6,929.52",
      "compareToPreviousClosePrice": "-167.37",
      "compareToPreviousPrice": {
        "code": "5",
        "text": "하락",
        "name": "FALLING"
      },
      "fluctuationsRatio": "-2.36",
      "openPrice": "7,000.78",
      "highPrice": "7,000.78",
      "lowPrice": "6,825.22",
      "accumulatedTradingVolume": "122,012천주",
      "accumulatedTradingValue": "8,147,119백만",
      "marketStatus": "OPEN",
      "localTradedAt": "2026-07-24T10:07:42+09:00",
      "symbolCode": "KOSPI",
      "fluctuationsRatioRaw": "-2.36",
      "openPriceRaw": "7000.78",
      "highPriceRaw": "7000.78",
      "lowPriceRaw": "6825.22",
      "accumulatedTradingVolumeRaw": "122012000",
      "accumulatedTradingValueRaw": "8147119000000",
      "closePriceRaw": "6929.52",
      "compareToPreviousClosePriceRaw": "-167.37"
    },
    {
      "itemCode": "KOSDAQ",
      "stockName": "코스닥",
      "stockExchangeType": {
        "code": "KQ",
        "zoneId": "Asia/Seoul",
        "nationType": "KOR",
        "delayTime": 0,
        "startTime": "0900",
        "endTime": "1530",
        "closePriceSendTime": "1630",
        "nameKor": "코스닥",
        "nameEng": "KOSDAQ",
        "nationCode": "KOR",
        "nationName": "대한민국",
        "stockType": "domestic",
        "name": "KOSDAQ"
      },
      "closePrice": "771.75",
      "compareToPreviousClosePrice": "-18.53",
      "compareToPreviousPrice": {
        "code": "5",
        "text": "하락",
        "name": "FALLING"
      },
      "fluctuationsRatio": "-2.34",
      "openPrice": "777.50",
      "highPrice": "777.50",
      "lowPrice": "763.07",
      "accumulatedTradingVolume": "210,865천주",
      "accumulatedTradingValue": "2,080,725백만",
      "marketStatus": "OPEN",
      "localTradedAt": "2026-07-24T10:07:42+09:00",
      "symbolCode": "KOSDAQ",
      "fluctuationsRatioRaw": "-2.34",
      "openPriceRaw": "777.50",
      "highPriceRaw": "777.50",
      "lowPriceRaw": "763.07",
      "accumulatedTradingVolumeRaw": "210865000",
      "accumulatedTradingValueRaw": "2080725000000",
      "closePriceRaw": "771.75",
      "compareToPreviousClosePriceRaw": "-18.53"
    }
  ],
  "worldIndex": [
    {
      "reutersCode": ".DJI",
      "indexName": "다우존스",
      "stockExchangeType": {
        "code": "NYS",
        "zoneId": "EST5EDT",
        "nationType": "USA",
        "delayTime": 0,
        "startTime": "0930",
        "endTime": "1600",
        "closePriceSendTime": "2031",
        "nameKor": "뉴욕 거래소",
        "nameEng": "New York Stock Exchange",
        "nationCode": "USA",
        "nationName": "미국",
        "stockType": "worldstock",
        "name": "NYSE"
      },
      "closePrice": "51,711.65",
      "compareToPreviousClosePrice": "-506.93",
      "compareToPreviousPrice": {
        "code": "5",
        "text": "하락",
        "name": "FALLING"
      },
      "fluctuationsRatio": "-0.97",
      "openPrice": "51,755.54",
      "highPrice": "51,885.14",
      "lowPrice": "51,542.06",
      "accumulatedTradingVolume": "496,579천주",
      "accumulatedTradingValue": "-",
      "marketStatus": "CLOSE",
      "localTradedAt": "2026-07-23T16:39:12-04:00",
      "symbolCode": "DJI",
      "fluctuationsRatioRaw": "-0.97",
      "openPriceRaw": "51755.54",
      "highPriceRaw": "51885.14",
      "lowPriceRaw": "51542.06",
      "accumulatedTradingVolumeRaw": "496579000",
      "accumulatedTradingValueRaw": "",
      "closePriceRaw": "51711.65",
      "compareToPreviousClosePriceRaw": "-506.93"
    },
    {
      "reutersCode": ".IXIC",
      "indexName": "나스닥 종합",
      "stockExchangeType": {
        "code": "NSQ",
        "zoneId": "EST5EDT",
        "nationType": "USA",
        "delayTime": 0,
        "startTime": "0930",
        "endTime": "1600",
        "closePriceSendTime": "2031",
        "nameKor": "나스닥 증권거래소",
        "nameEng": "NASDAQ Stock Exchange",
        "nationCode": "USA",
        "nationName": "미국",
        "stockType": "worldstock",
        "name": "NASDAQ"
      },
      "closePrice": "25,137.69",
      "compareToPreviousClosePrice": "-553.21",
      "compareToPreviousPrice": {
        "code": "5",
        "text": "하락",
        "name": "FALLING"
      },
      "fluctuationsRatio": "-2.15",
      "openPrice": "25,245.54",
      "highPrice": "25,358.28",
      "lowPrice": "24,954.77",
      "accumulatedTradingVolume": "1,455,852천주",
      "accumulatedTradingValue": "-",
      "marketStatus": "CLOSE",
      "localTradedAt": "2026-07-23T17:15:59-04:00",
      "symbolCode": "IXIC",
      "fluctuationsRatioRaw": "-2.15",
      "openPriceRaw": "25245.54",
      "highPriceRaw": "25358.28",
      "lowPriceRaw": "24954.77",
      "accumulatedTradingVolumeRaw": "1455852000",
      "accumulatedTradingValueRaw": "",
      "closePriceRaw": "25137.69",
      "compareToPreviousClosePriceRaw": "-553.21"
    },
    {
      "reutersCode": ".INX",
      "indexName": "S&P 500",
      "stockExchangeType": {
        "code": "NYS",
        "zoneId": "EST5EDT",
        "nationType": "USA",
        "delayTime": 0,
        "startTime": "0930",
        "endTime": "1600",
        "closePriceSendTime": "2031",
        "nameKor": "뉴욕 거래소",
        "nameEng": "New York Stock Exchange",
        "nationCode": "USA",
        "nationName": "미국",
        "stockType": "worldstock",
        "name": "NYSE"
      },
      "closePrice": "7,408.30",
      "compareToPreviousClosePrice": "-90.66",
      "compareToPreviousPrice": {
        "code": "5",
        "text": "하락",
        "name": "FALLING"
      },
      "fluctuationsRatio": "-1.21",
      "openPrice": "7,418.29",
      "highPrice": "7,450.12",
      "lowPrice": "7,376.00",
      "accumulatedTradingVolume": "3,325,093천주",
      "accumulatedTradingValue": "-",
      "marketStatus": "CLOSE",
      "localTradedAt": "2026-07-23T16:39:07-04:00",
      "symbolCode": "SPX",
      "fluctuationsRatioRaw": "-1.21",
      "openPriceRaw": "7418.29",
      "highPriceRaw": "7450.12",
      "lowPriceRaw": "7376.00",
      "accumulatedTradingVolumeRaw": "3325093000",
      "accumulatedTradingValueRaw": "",
      "closePriceRaw": "7408.30",
      "compareToPreviousClosePriceRaw": "-90.66"
    }
  ],
  "usStocks": [
    {
      "reutersCode": "AAPL.O",
      "stockName": "애플",
      "symbolCode": "AAPL",
      "stockExchangeType": {
        "code": "NSQ",
        "zoneId": "EST5EDT",
        "nationType": "USA",
        "delayTime": 0,
        "startTime": "0930",
        "endTime": "1600",
        "closePriceSendTime": "2031",
        "nameKor": "나스닥 증권거래소",
        "nameEng": "NASDAQ Stock Exchange",
        "nationCode": "USA",
        "nationName": "미국",
        "stockType": "worldstock",
        "name": "NASDAQ"
      },
      "closePrice": "321.66",
      "compareToPreviousClosePrice": "-4.23",
      "compareToPreviousPrice": {
        "code": "5",
        "text": "하락",
        "name": "FALLING"
      },
      "fluctuationsRatio": "-1.30",
      "tradeStopType": {
        "code": "1",
        "text": "운영.Trading",
        "name": "TRADING"
      },
      "tradableStatus": "tradable",
      "tradableStatusCode": "ok",
      "tradableStatusUpdatedAt": null,
      "openPrice": "321.73",
      "highPrice": "323.30",
      "lowPrice": "319.35",
      "accumulatedTradingVolume": "40,840,778",
      "accumulatedTradingValue": "131억 USD",
      "localTradedAt": "2026-07-23T16:00:00-04:00",
      "marketStatus": "CLOSE",
      "overMarketPriceInfo": {
        "tradingSessionType": "AFTER_MARKET",
        "overMarketStatus": "CLOSE",
        "overPrice": "321.10",
        "compareToPreviousPrice": {
          "code": "5",
          "text": "하락",
          "name": "FALLING"
        },
        "compareToPreviousClosePrice": "-0.56",
        "fluctuationsRatio": "-0.17",
        "localTradedAt": "2026-07-23T20:00:00-04:00"
      },
      "currencyType": {
        "code": "USD",
        "text": "US dollar",
        "name": "USD"
      },
      "isinCode": "US0378331005",
      "myDataCode": null,
      "stockEndUrl": null,
      "marketValueFull": "4,724,334,930,960",
      "marketValueHangeul": "4조 7,243억 USD",
      "marketValueKrwHangeul": "6,930조 1,269억원",
      "marketValueKrwRaw": "6930126910225224",
      "accumulatedTradingValueKrwRaw": "19244582351100",
      "lowPriceRaw": "319.35",
      "marketValueFullRaw": "4724334930960",
      "accumulatedTradingVolumeRaw": "40840778",
      "accumulatedTradingValueRaw": "13119219000",
      "compareToPreviousClosePriceRaw": "-4.23",
      "closePriceRaw": "321.66",
      "fluctuationsRatioRaw": "-1.30",
      "openPriceRaw": "321.73",
      "highPriceRaw": "323.30"
    },
    {
      "reutersCode": "MSFT.O",
      "stockName": "마이크로소프트",
      "symbolCode": "MSFT",
      "stockExchangeType": {
        "code": "NSQ",
        "zoneId": "EST5EDT",
        "nationType": "USA",
        "delayTime": 0,
        "startTime": "0930",
        "endTime": "1600",
        "closePriceSendTime": "2031",
        "nameKor": "나스닥 증권거래소",
        "nameEng": "NASDAQ Stock Exchange",
        "nationCode": "USA",
        "nationName": "미국",
        "stockType": "worldstock",
        "name": "NASDAQ"
      },
      "closePrice": "381.58",
      "compareToPreviousClosePrice": "-8.76",
      "compareToPreviousPrice": {
        "code": "5",
        "text": "하락",
        "name": "FALLING"
      },
      "fluctuationsRatio": "-2.24",
      "tradeStopType": {
        "code": "1",
        "text": "운영.Trading",
        "name": "TRADING"
      },
      "tradableStatus": "tradable",
      "tradableStatusCode": "ok",
      "tradableStatusUpdatedAt": null,
      "openPrice": "389.97",
      "highPrice": "391.78",
      "lowPrice": "377.39",
      "accumulatedTradingVolume": "30,351,752",
      "accumulatedTradingValue": "116억 USD",
      "localTradedAt": "2026-07-23T16:00:00-04:00",
      "marketStatus": "CLOSE",
      "overMarketPriceInfo": {
        "tradingSessionType": "AFTER_MARKET",
        "overMarketStatus": "CLOSE",
        "overPrice": "382.43",
        "compareToPreviousPrice": {
          "code": "2",
          "text": "상승",
          "name": "RISING"
        },
        "compareToPreviousClosePrice": "0.85",
        "fluctuationsRatio": "0.22",
        "localTradedAt": "2026-07-23T20:00:00-04:00"
      },
      "currencyType": {
        "code": "USD",
        "text": "US dollar",
        "name": "USD"
      },
      "isinCode": "US5949181045",
      "myDataCode": null,
      "stockEndUrl": null,
      "marketValueFull": "2,834,542,114,352",
      "marketValueHangeul": "2조 8,345억 USD",
      "marketValueKrwHangeul": "4,157조 9,898억원",
      "marketValueKrwRaw": "4157989827542949",
      "accumulatedTradingValueKrwRaw": "17019661776100",
      "lowPriceRaw": "377.39",
      "marketValueFullRaw": "2834542114352",
      "accumulatedTradingVolumeRaw": "30351752",
      "accumulatedTradingValueRaw": "11602469000",
      "compareToPreviousClosePriceRaw": "-8.76",
      "closePriceRaw": "381.58",
      "fluctuationsRatioRaw": "-2.24",
      "openPriceRaw": "389.97",
      "highPriceRaw": "391.78"
    },
    {
      "reutersCode": "GOOG.O",
      "stockName": "알파벳 Class C",
      "symbolCode": "GOOG",
      "stockExchangeType": {
        "code": "NSQ",
        "zoneId": "EST5EDT",
        "nationType": "USA",
        "delayTime": 0,
        "startTime": "0930",
        "endTime": "1600",
        "closePriceSendTime": "2031",
        "nameKor": "나스닥 증권거래소",
        "nameEng": "NASDAQ Stock Exchange",
        "nationCode": "USA",
        "nationName": "미국",
        "stockType": "worldstock",
        "name": "NASDAQ"
      },
      "closePrice": "318.34",
      "compareToPreviousClosePrice": "-23.57",
      "compareToPreviousPrice": {
        "code": "5",
        "text": "하락",
        "name": "FALLING"
      },
      "fluctuationsRatio": "-6.89",
      "tradeStopType": {
        "code": "1",
        "text": "운영.Trading",
        "name": "TRADING"
      },
      "tradableStatus": "tradable",
      "tradableStatusCode": "ok",
      "tradableStatusUpdatedAt": null,
      "openPrice": "321.63",
      "highPrice": "324.45",
      "lowPrice": "314.89",
      "accumulatedTradingVolume": "46,751,948",
      "accumulatedTradingValue": "150억 USD",
      "localTradedAt": "2026-07-23T16:00:00-04:00",
      "marketStatus": "CLOSE",
      "overMarketPriceInfo": {
        "tradingSessionType": "AFTER_MARKET",
        "overMarketStatus": "CLOSE",
        "overPrice": "319.48",
        "compareToPreviousPrice": {
          "code": "2",
          "text": "상승",
          "name": "RISING"
        },
        "compareToPreviousClosePrice": "1.14",
        "fluctuationsRatio": "0.36",
        "localTradedAt": "2026-07-23T20:00:00-04:00"
      },
      "currencyType": {
        "code": "USD",
        "text": "US dollar",
        "name": "USD"
      },
      "isinCode": "US02079K1079",
      "myDataCode": null,
      "stockEndUrl": null,
      "marketValueFull": "1,759,465,180,000",
      "marketValueHangeul": "1조 7,595억 USD",
      "marketValueKrwHangeul": "2,580조 9,595억원",
      "marketValueKrwRaw": "2580959472542000",
      "accumulatedTradingValueKrwRaw": "21957943953600",
      "lowPriceRaw": "314.89",
      "marketValueFullRaw": "1759465180000",
      "accumulatedTradingVolumeRaw": "46751948",
      "accumulatedTradingValueRaw": "14968944000",
      "compareToPreviousClosePriceRaw": "-23.57",
      "closePriceRaw": "318.34",
      "fluctuationsRatioRaw": "-6.89",
      "openPriceRaw": "321.63",
      "highPriceRaw": "324.45"
    },
    {
      "reutersCode": "AMZN.O",
      "stockName": "아마존닷컴",
      "symbolCode": "AMZN",
      "stockExchangeType": {
        "code": "NSQ",
        "zoneId": "EST5EDT",
        "nationType": "USA",
        "delayTime": 0,
        "startTime": "0930",
        "endTime": "1600",
        "closePriceSendTime": "2031",
        "nameKor": "나스닥 증권거래소",
        "nameEng": "NASDAQ Stock Exchange",
        "nationCode": "USA",
        "nationName": "미국",
        "stockType": "worldstock",
        "name": "NASDAQ"
      },
      "closePrice": "233.66",
      "compareToPreviousClosePrice": "-11.19",
      "compareToPreviousPrice": {
        "code": "5",
        "text": "하락",
        "name": "FALLING"
      },
      "fluctuationsRatio": "-4.57",
      "tradeStopType": {
        "code": "1",
        "text": "운영.Trading",
        "name": "TRADING"
      },
      "tradableStatus": "tradable",
      "tradableStatusCode": "ok",
      "tradableStatusUpdatedAt": null,
      "openPrice": "236.26",
      "highPrice": "238.35",
      "lowPrice": "232.05",
      "accumulatedTradingVolume": "47,465,337",
      "accumulatedTradingValue": "111억 USD",
      "localTradedAt": "2026-07-23T16:00:00-04:00",
      "marketStatus": "CLOSE",
      "overMarketPriceInfo": {
        "tradingSessionType": "AFTER_MARKET",
        "overMarketStatus": "CLOSE",
        "overPrice": "234.45",
        "compareToPreviousPrice": {
          "code": "2",
          "text": "상승",
          "name": "RISING"
        },
        "compareToPreviousClosePrice": "0.79",
        "fluctuationsRatio": "0.34",
        "localTradedAt": "2026-07-23T20:00:00-04:00"
      },
      "currencyType": {
        "code": "USD",
        "text": "US dollar",
        "name": "USD"
      },
      "isinCode": "US0231351067",
      "myDataCode": null,
      "stockEndUrl": null,
      "marketValueFull": "2,513,506,190,816",
      "marketValueHangeul": "2조 5,135억 USD",
      "marketValueKrwHangeul": "3,687조 622억원",
      "marketValueKrwRaw": "3687062231307990",
      "accumulatedTradingValueKrwRaw": "16310537378800",
      "lowPriceRaw": "232.05",
      "marketValueFullRaw": "2513506190816",
      "accumulatedTradingVolumeRaw": "47465337",
      "accumulatedTradingValueRaw": "11119052000",
      "compareToPreviousClosePriceRaw": "-11.19",
      "closePriceRaw": "233.66",
      "fluctuationsRatioRaw": "-4.57",
      "openPriceRaw": "236.26",
      "highPriceRaw": "238.35"
    },
    {
      "reutersCode": "NVDA.O",
      "stockName": "엔비디아",
      "symbolCode": "NVDA",
      "stockExchangeType": {
        "code": "NSQ",
        "zoneId": "EST5EDT",
        "nationType": "USA",
        "delayTime": 0,
        "startTime": "0930",
        "endTime": "1600",
        "closePriceSendTime": "2031",
        "nameKor": "나스닥 증권거래소",
        "nameEng": "NASDAQ Stock Exchange",
        "nationCode": "USA",
        "nationName": "미국",
        "stockType": "worldstock",
        "name": "NASDAQ"
      },
      "closePrice": "208.76",
      "compareToPreviousClosePrice": "-3.30",
      "compareToPreviousPrice": {
        "code": "5",
        "text": "하락",
        "name": "FALLING"
      },
      "fluctuationsRatio": "-1.56",
      "tradeStopType": {
        "code": "1",
        "text": "운영.Trading",
        "name": "TRADING"
      },
      "tradableStatus": "tradable",
      "tradableStatusCode": "ok",
      "tradableStatusUpdatedAt": null,
      "openPrice": "209.46",
      "highPrice": "210.87",
      "lowPrice": "205.96",
      "accumulatedTradingVolume": "110,505,328",
      "accumulatedTradingValue": "230억 USD",
      "localTradedAt": "2026-07-23T16:00:00-04:00",
      "marketStatus": "CLOSE",
      "overMarketPriceInfo": {
        "tradingSessionType": "AFTER_MARKET",
        "overMarketStatus": "CLOSE",
        "overPrice": "207.99",
        "compareToPreviousPrice": {
          "code": "5",
          "text": "하락",
          "name": "FALLING"
        },
        "compareToPreviousClosePrice": "-0.77",
        "fluctuationsRatio": "-0.37",
        "localTradedAt": "2026-07-23T20:00:00-04:00"
      },
      "currencyType": {
        "code": "USD",
        "text": "US dollar",
        "name": "USD"
      },
      "isinCode": "US67066G1040",
      "myDataCode": null,
      "stockEndUrl": null,
      "marketValueFull": "5,051,992,000,000",
      "marketValueHangeul": "5조 520억 USD",
      "marketValueKrwHangeul": "7,410조 7,671억원",
      "marketValueKrwRaw": "7410767064800000",
      "accumulatedTradingValueKrwRaw": "33810374200900",
      "lowPriceRaw": "205.96",
      "marketValueFullRaw": "5051992000000",
      "accumulatedTradingVolumeRaw": "110505328",
      "accumulatedTradingValueRaw": "23048861000",
      "compareToPreviousClosePriceRaw": "-3.30",
      "closePriceRaw": "208.76",
      "fluctuationsRatioRaw": "-1.56",
      "openPriceRaw": "209.46",
      "highPriceRaw": "210.87"
    },
    {
      "reutersCode": "META.O",
      "stockName": "메타",
      "symbolCode": "META",
      "stockExchangeType": {
        "code": "NSQ",
        "zoneId": "EST5EDT",
        "nationType": "USA",
        "delayTime": 0,
        "startTime": "0930",
        "endTime": "1600",
        "closePriceSendTime": "2031",
        "nameKor": "나스닥 증권거래소",
        "nameEng": "NASDAQ Stock Exchange",
        "nationCode": "USA",
        "nationName": "미국",
        "stockType": "worldstock",
        "name": "NASDAQ"
      },
      "closePrice": "606.10",
      "compareToPreviousClosePrice": "-21.07",
      "compareToPreviousPrice": {
        "code": "5",
        "text": "하락",
        "name": "FALLING"
      },
      "fluctuationsRatio": "-3.36",
      "tradeStopType": {
        "code": "1",
        "text": "운영.Trading",
        "name": "TRADING"
      },
      "tradableStatus": "tradable",
      "tradableStatusCode": "ok",
      "tradableStatusUpdatedAt": null,
      "openPrice": "608.41",
      "highPrice": "614.65",
      "lowPrice": "597.22",
      "accumulatedTradingVolume": "15,494,842",
      "accumulatedTradingValue": "93.8억 USD",
      "localTradedAt": "2026-07-23T16:00:00-04:00",
      "marketStatus": "CLOSE",
      "overMarketPriceInfo": {
        "tradingSessionType": "AFTER_MARKET",
        "overMarketStatus": "CLOSE",
        "overPrice": "606.86",
        "compareToPreviousPrice": {
          "code": "2",
          "text": "상승",
          "name": "RISING"
        },
        "compareToPreviousClosePrice": "0.76",
        "fluctuationsRatio": "0.13",
        "localTradedAt": "2026-07-23T20:00:00-04:00"
      },
      "currencyType": {
        "code": "USD",
        "text": "US dollar",
        "name": "USD"
      },
      "isinCode": "US30303M1027",
      "myDataCode": null,
      "stockEndUrl": null,
      "marketValueFull": "1,538,538,364,554",
      "marketValueHangeul": "1조 5,385억 USD",
      "marketValueKrwHangeul": "2,256조 8,819억원",
      "marketValueKrwRaw": "2256881926964263",
      "accumulatedTradingValueKrwRaw": "13765116756600",
      "lowPriceRaw": "597.22",
      "marketValueFullRaw": "1538538364554",
      "accumulatedTradingVolumeRaw": "15494842",
      "accumulatedTradingValueRaw": "9383814000",
      "compareToPreviousClosePriceRaw": "-21.07",
      "closePriceRaw": "606.10",
      "fluctuationsRatioRaw": "-3.36",
      "openPriceRaw": "608.41",
      "highPriceRaw": "614.65"
    },
    {
      "reutersCode": "TSLA.O",
      "stockName": "테슬라",
      "symbolCode": "TSLA",
      "stockExchangeType": {
        "code": "NSQ",
        "zoneId": "EST5EDT",
        "nationType": "USA",
        "delayTime": 0,
        "startTime": "0930",
        "endTime": "1600",
        "closePriceSendTime": "2031",
        "nameKor": "나스닥 증권거래소",
        "nameEng": "NASDAQ Stock Exchange",
        "nationCode": "USA",
        "nationName": "미국",
        "stockType": "worldstock",
        "name": "NASDAQ"
      },
      "closePrice": "319.69",
      "compareToPreviousClosePrice": "-54.32",
      "compareToPreviousPrice": {
        "code": "5",
        "text": "하락",
        "name": "FALLING"
      },
      "fluctuationsRatio": "-14.52",
      "tradeStopType": {
        "code": "1",
        "text": "운영.Trading",
        "name": "TRADING"
      },
      "tradableStatus": "tradable",
      "tradableStatusCode": "ok",
      "tradableStatusUpdatedAt": null,
      "openPrice": "341.00",
      "highPrice": "342.11",
      "lowPrice": "315.74",
      "accumulatedTradingVolume": "115,606,413",
      "accumulatedTradingValue": "376억 USD",
      "localTradedAt": "2026-07-23T16:00:00-04:00",
      "marketStatus": "CLOSE",
      "overMarketPriceInfo": {
        "tradingSessionType": "AFTER_MARKET",
        "overMarketStatus": "CLOSE",
        "overPrice": "324.00",
        "compareToPreviousPrice": {
          "code": "2",
          "text": "상승",
          "name": "RISING"
        },
        "compareToPreviousClosePrice": "4.31",
        "fluctuationsRatio": "1.35",
        "localTradedAt": "2026-07-23T20:00:00-04:00"
      },
      "currencyType": {
        "code": "USD",
        "text": "US dollar",
        "name": "USD"
      },
      "isinCode": "US88160R1014",
      "myDataCode": null,
      "stockEndUrl": null,
      "marketValueFull": "1,200,667,364,320",
      "marketValueHangeul": "1조 2,007억 USD",
      "marketValueKrwHangeul": "1,761조 2,590억원",
      "marketValueKrwRaw": "1761258956721008",
      "accumulatedTradingValueKrwRaw": "55179126034300",
      "lowPriceRaw": "315.74",
      "marketValueFullRaw": "1200667364320",
      "accumulatedTradingVolumeRaw": "115606413",
      "accumulatedTradingValueRaw": "37616147000",
      "compareToPreviousClosePriceRaw": "-54.32",
      "closePriceRaw": "319.69",
      "fluctuationsRatioRaw": "-14.52",
      "openPriceRaw": "341.00",
      "highPriceRaw": "342.11"
    }
  ],
  "krStocks": [
    {
      "itemCode": "005930",
      "stockName": "삼성전자",
      "stockExchangeType": {
        "code": "KS",
        "zoneId": "Asia/Seoul",
        "nationType": "KOR",
        "delayTime": 0,
        "startTime": "0900",
        "endTime": "1530",
        "closePriceSendTime": "1630",
        "nameKor": "코스피",
        "nameEng": "KOSPI",
        "nationCode": "KOR",
        "nationName": "대한민국",
        "stockType": "domestic",
        "name": "KOSPI"
      },
      "closePrice": "260,500",
      "compareToPreviousClosePrice": "-9,500",
      "compareToPreviousPrice": {
        "code": "5",
        "text": "하락",
        "name": "FALLING"
      },
      "fluctuationsRatio": "-3.52",
      "tradeStopType": {
        "code": "1",
        "text": "운영.Trading",
        "name": "TRADING"
      },
      "tradableStatus": "tradable",
      "tradableStatusCode": "ok",
      "tradableStatusUpdatedAt": "2026-07-24T08:01:26.724+09:00",
      "openPrice": "266,000",
      "highPrice": "266,500",
      "lowPrice": "257,000",
      "accumulatedTradingVolume": "5,192,393",
      "accumulatedTradingValue": "1조 3,535억",
      "marketStatus": "OPEN",
      "localTradedAt": "2026-07-24T10:07:45.471909+09:00",
      "overMarketPriceInfo": {
        "tradingSessionType": "REGULAR_MARKET",
        "overMarketStatus": "OPEN",
        "overPrice": "260,500",
        "openPrice": "268,000",
        "highPrice": "269,500",
        "lowPrice": "257,500",
        "compareToPreviousPrice": {
          "code": "5",
          "text": "하락",
          "name": "FALLING"
        },
        "compareToPreviousClosePrice": "-9,500",
        "fluctuationsRatio": "-3.52",
        "localTradedAt": "2026-07-24T10:07:45.471929+09:00",
        "tradeStopType": {
          "code": "1",
          "text": "운영.Trading",
          "name": "TRADING"
        },
        "tradableStatus": "tradable",
        "tradableStatusCode": "ok",
        "tradableStatusUpdatedAt": "2026-07-24T07:10:12.669+09:00",
        "accumulatedTradingVolume": "5,153,426",
        "accumulatedTradingValue": "1조 3,575억",
        "accumulatedTradingValueRaw": "1357504000000",
        "accumulatedTradingVolumeRaw": "5153426"
      },
      "integratedPriceInfo": {
        "openPrice": "268,000",
        "highPrice": "269,500",
        "lowPrice": "257,000",
        "accumulatedTradingVolume": "10,345,819",
        "accumulatedTradingValue": "2조 7,110억",
        "accumulatedTradingValueRaw": "2710954000000",
        "accumulatedTradingVolumeRaw": "10345819"
      },
      "isinCode": "KR7005930003",
      "myDataCode": null,
      "stockEndUrl": null,
      "symbolCode": "005930",
      "currencyType": {
        "code": "KRW",
        "text": "Republic of Korea won",
        "name": "KRW"
      },
      "closePriceRaw": "260500",
      "fluctuationsRatioRaw": "-3.52",
      "accumulatedTradingValueRaw": "1353450000000",
      "accumulatedTradingVolumeRaw": "5192393",
      "compareToPreviousClosePriceRaw": "-9500",
      "marketValueFull": "1,522,955,577,384,000",
      "marketValueFullRaw": "1522955577384000",
      "lowPriceRaw": "257000",
      "highPriceRaw": "266500",
      "openPriceRaw": "266000"
    },
    {
      "itemCode": "000660",
      "stockName": "SK하이닉스",
      "stockExchangeType": {
        "code": "KS",
        "zoneId": "Asia/Seoul",
        "nationType": "KOR",
        "delayTime": 0,
        "startTime": "0900",
        "endTime": "1530",
        "closePriceSendTime": "1630",
        "nameKor": "코스피",
        "nameEng": "KOSPI",
        "nationCode": "KOR",
        "nationName": "대한민국",
        "stockType": "domestic",
        "name": "KOSPI"
      },
      "closePrice": "1,855,000",
      "compareToPreviousClosePrice": "-64,000",
      "compareToPreviousPrice": {
        "code": "5",
        "text": "하락",
        "name": "FALLING"
      },
      "fluctuationsRatio": "-3.34",
      "tradeStopType": {
        "code": "1",
        "text": "운영.Trading",
        "name": "TRADING"
      },
      "tradableStatus": "tradable",
      "tradableStatusCode": "ok",
      "tradableStatusUpdatedAt": "2026-07-24T08:01:19.22+09:00",
      "openPrice": "1,894,000",
      "highPrice": "1,894,000",
      "lowPrice": "1,810,000",
      "accumulatedTradingVolume": "1,208,959",
      "accumulatedTradingValue": "2조 2,285억",
      "marketStatus": "OPEN",
      "localTradedAt": "2026-07-24T10:07:45.471916+09:00",
      "overMarketPriceInfo": {
        "tradingSessionType": "REGULAR_MARKET",
        "overMarketStatus": "OPEN",
        "overPrice": "1,854,000",
        "openPrice": "1,900,000",
        "highPrice": "1,909,000",
        "lowPrice": "1,810,000",
        "compareToPreviousPrice": {
          "code": "5",
          "text": "하락",
          "name": "FALLING"
        },
        "compareToPreviousClosePrice": "-65,000",
        "fluctuationsRatio": "-3.39",
        "localTradedAt": "2026-07-24T10:07:45.471939+09:00",
        "tradeStopType": {
          "code": "1",
          "text": "운영.Trading",
          "name": "TRADING"
        },
        "tradableStatus": "tradable",
        "tradableStatusCode": "ok",
        "tradableStatusUpdatedAt": "2026-07-24T07:10:11.248+09:00",
        "accumulatedTradingVolume": "1,040,198",
        "accumulatedTradingValue": "1조 9,421억",
        "accumulatedTradingValueRaw": "1942054000000",
        "accumulatedTradingVolumeRaw": "1040198"
      },
      "integratedPriceInfo": {
        "openPrice": "1,900,000",
        "highPrice": "1,909,000",
        "lowPrice": "1,810,000",
        "accumulatedTradingVolume": "2,249,157",
        "accumulatedTradingValue": "4조 1,706억",
        "accumulatedTradingValueRaw": "4170575000000",
        "accumulatedTradingVolumeRaw": "2249157"
      },
      "isinCode": "KR7000660001",
      "myDataCode": null,
      "stockEndUrl": null,
      "symbolCode": "000660",
      "currencyType": {
        "code": "KRW",
        "text": "Republic of Korea won",
        "name": "KRW"
      },
      "closePriceRaw": "1855000",
      "fluctuationsRatioRaw": "-3.34",
      "accumulatedTradingValueRaw": "2228521000000",
      "accumulatedTradingVolumeRaw": "1208959",
      "compareToPreviousClosePriceRaw": "-64000",
      "marketValueFull": "1,322,062,887,075,000",
      "marketValueFullRaw": "1322062887075000",
      "lowPriceRaw": "1810000",
      "highPriceRaw": "1894000",
      "openPriceRaw": "1894000"
    }
  ]
}